geodis
