Metadata-Version: 1.0
Name: geodis
Version: 2.0.9
Summary: A fast Redis based Geo resolving library
Home-page: https://github.com/EverythingMe/geodis
Author: DoAT Media LTD.
Author-email: opensource@everything.me
License: UNKNOWN
Platform: UNKNOWN
